{
  "sections": [
    {
      "id": "stuti",
      "verses": [
        { "id": 1, "first": "પ્રથમં શૈલપુત્રી ચ", "second": "દ્વિતીયં બ્રહ્મચારિણી" },
        { "id": 2, "first": "તૃતીયં ચંદ્રઘંટેતિ", "second": "કૂષ્માંડેતિ ચતુર્થકમ" },
        { "id": 3, "first": "પંચમં સ્કંદમાતા ચ", "second": "ષષ્ઠમ કાત્યાયની તથા" },
        { "id": 4, "first": "સપ્તમં કાલરાત્રિ ચ", "second": "મહાગૌરી ચ અષ્ટમમ" },
        { "id": 5, "first": "નવમં સિદ્ધિદાત્રી ચ", "second": "નવદુર્ગા પ્રકીર્તિતાઃ" },
        { "id": 6, "first": "ઉક્તાન્યેતાનિ નામાનિ", "second": "બ્રહ્મણૈવ મહાત્મના" },
        { "id": 7, "first": "શૈલપુત્રી શુભં દદ્યાત", "second": "બ્રહ્મચારિણી સતમ" },
        { "id": 8, "first": "ચંદ્રઘંટા શુભં દદ્યાત", "second": "કૂષ્માંડા આરોગ્યમ એવ ચ" },
        { "id": 9, "first": "સ્કંદમાતા સુખં દદ્યાત", "second": "કાત્યાયની યશો બલમ" },
        { "id": 10, "first": "કાલરાત્રિ શુભં દદ્યાત", "second": "મહાગૌરી તુ નિષ્કલમ" },
        { "id": 11, "first": "સિદ્ધિદાત્રી ચ સિદ્ધિમ", "second": "દદ્યાત પુણ્યં તથા" },
        { "id": 12, "first": "નવદુર્ગા નમસ્યામિ", "second": "નવદુર્ગા મહોત્સવમ" }
      ]
    }
  ]
}
